Workbook
Name Slicer_genre.genre: #N/A

Sheet movie
A1: MOV-ID | B1: title | C1: year | D1: parental_guide | E1: runtime | F1: gross_us_canada
A2: 0111161 | B2: The Shawshank Redemption | C2: 1994 | D2: R | E2: 142 | F2: $28,767,189
A3: 0068646 | B3: The Godfather | C3: 1972 | D3: R | E3: 175 | F3: $136,381,073
A4: 0468569 | B4: The Dark Knight | C4: 2008 | D4: PG-13 | E4: 152 | F4: $534,987,076
A5: 0071562 | B5: The Godfather Part II | C5: 1974 | D5: R | E5: 202 | F5: $47,834,595
A6: 0050083 | B6: 12 Angry Men | C6: 1957 | D6: Approved | E6: 96 | F6: $2,945
A7: 0167260 | B7: The Lord of the Rings: The Return of the King | C7: 2003 | D7: PG-13 | E7: 201 | F7: $381,878,219
A8: 0108052 | B8: Schindler's List | C8: 1993 | D8: R | E8: 195 | F8: $96,898,818
A9: 0120737 | B9: The Lord of the Rings: The Fellowship of the Ring | C9: 2001 | D9: PG-13 | E9: 178 | F9: $319,372,078
A10: 0110912 | B10: Pulp Fiction | C10: 1994 | D10: R | E10: 154 | F10: $107,928,762
A11: 0060196 | B11: The Good, the Bad and the Ugly | C11: 1966 | D11: R | E11: 178 | F11: $25,100,000
A12: 0109830 | B12: Forrest Gump | C12: 1994 | D12: PG-13 | E12: 142 | F12: $330,455,270
A13: 0167261 | B13: The Lord of the Rings: The Two Towers | C13: 2002 | D13: PG-13 | E13: 179 | F13: $345,518,923
... A69: 0361748 | B69: Inglourious Basterds | C69: 2009 | D69: R | E69: 153 | F69: $120,540,719
A70: 23849204 | B70: 12th Fail | C70: 2023 | D70: N/A | E70: 147 | F70: N/A
A71: 0090605 | B71: Aliens | C71: 1986 | D71: R | E71: 137 | F71: $85,160,248
A72: 1345836 | B72: The Dark Knight Rises | C72: 2012 | D72: PG-13 | E72: 164 | F72: $448,149,584
A73: 2380307 | B73: Coco | C73: 2017 | D73: PG | E73: 105 | F73: $210,460,015
A74: 0086879 | B74: Amadeus | C74: 1984 | D74: PG | E74: 160 | F74: $51,973,029
A75: 4154796 | B75: Avengers: Endgame | C75: 2019 | D75: PG-13 | E75: 181 | F75: $858,373,000
A76: 0119217 | B76: Good Will Hunting | C76: 1997 | D76: R | E76: 126 | F76: $138,433,435
A77: 0114709 | B77: Toy Story | C77: 1995 | D77: G | E77: 81 | F77: $227,280,221
A78: 0057565 | B78: High and Low | C78: 1963 | D78: Not Rated | E78: 143 | F78: $46,808
A79: 0364569 | B79: Oldboy | C79: 2003 | D79: R | E79: 120 | F79: $2,458,200
A80: 0057012 | B80: Dr. Strangelove or: How I Learned to Stop Worrying and Love the Bomb | C80: 1964 | D80: PG | E80: 95 | F80: $9,440,272
A81: 0082096 | B81: Das Boot | C81: 1981 | D81: N/A | E81: 149 | F81: $11,487,676
A82: 0112573 | B82: Braveheart | C82: 1995 | D82: R | E82: 178 | F82: $75,609,945
A83: 5311514 | B83: Your Name. | C83: 2016 | D83: N/A | E83: 106 | F83: $5,017,246
A84: 0119698 | B84: Princess Mononoke | C84: 1997 | D84: PG-13 | E84: 133 | F84: $11,696,687
A85: 0169547 | B85: American Beauty | C85: 1999 | D85: R | E85: 122 | F85: $130,096,601
A86: 1187043 | B86: 3 Idiots | C86: 2009 | D86: PG-13 | E86: 170 | F86: $6,532,874
A87: 7286456 | B87: Joker | C87: 2019 | D87: R | E87: 122 | F87: $335,477,657
A88: 8267604 | B88: Capernaum | C88: 2018 | D88: R | E88: 126 | F88: $1,661,096
A89: 0087843 | B89: Once Upon a Time in America | C89: 1984 | D89: R | E89: 229 | F89: $5,321,508
A90: 0045152 | B90: Singin' in the Rain | C90: 1952 | D90: G | E90: 103 | F90: $1,884,537
A91: 0091251 | B91: Come and See | C91: 1985 | D91: Not Rated | E91: 142 | F91: $16,053
A92: 0180093 | B92: Requiem for a Dream | C92: 2000 | D92: NC-17 | E92: 102 | F92: $3,635,482
A93: 0086190 | B93: Star Wars: Episode VI - Return of the Jedi | C93: 1983 | D93: PG | E93: 131 | F93: $316,566,101
A94: 0435761 | B94: Toy Story 3 | C94: 2010 | D94: G | E94: 103 | F94: $415,004,880
A95: 2106476 | B95: The Hunt | C95: 2012 | D95: R | E95: 115 | F95: $613,308
... A217: 1895587 | B217: Spotlight | C217: 2015 | D217: R | E217: 129 | F217: $45,055,776
A218: 26548265 | B218: Maharaja | C218: 2024 | D218: N/A | E218: 141 | F218: $975,543
A219: 0325980 | B219: Pirates of the Caribbean: The Curse of the Black Pearl | C219: 2003 | D219: PG-13 | E219: 143 | F219: $305,413,918
A220: 0088247 | B220: The Terminator | C220: 1984 | D220: R | E220: 107 | F220: $38,371,200
A221: 0113247 | B221: La haine | C221: 1995 | D221: Not Rated | E221: 98 | F221: $280,859
A222: 0118715 | B222: The Big Lebowski | C222: 1998 | D222: R | E222: 117 | F222: $19,488,923
A223: 15097216 | B223: Jai Bhim | C223: 2021 | D223: Approved | E223: 164 | F223: N/A
A224: 0050976 | B224: The Seventh Seal | C224: 1957 | D224: Not Rated | E224: 96 | F224: $312,104
A225: 3170832 | B225: Room | C225: 2015 | D225: R | E225: 118 | F225: $14,677,654
A226: 32820897 | B226: Demon Slayer: Kimetsu no Yaiba - Infinity Castle | C226: 2025 | D226: R | E226: 155 | F226: $70,611,098
A227: 0395169 | B227: Hotel Rwanda | C227: 2004 | D227: PG-13 | E227: 121 | F227: $23,530,892
A228: 0091763 | B228: Platoon | C228: 1986 | D228: R | E228: 120 | F228: $138,530,565
A229: 0036868 | B229: The Best Years of Our Lives | C229: 1946 | D229: Approved | E229: 170 | F229: $23,650,000
A230: 0381681 | B230: Before Sunset | C230: 2004 | D230: R | E230: 80 | F230: $5,820,649
... A247: 0035446 | B247: To Be or Not to Be | C247: 1942 | D247: Approved | E247: 99 | F247: $4,578,000
A248: 16492678 | B248: Demon Slayer: Kimetsu no Yaiba - Tsuzumi Mansion Arc | C248: 2021 | D248: N/A | E248: 87 | F248: N/A
A249: 0758758 | B249: Into the Wild | C249: 2007 | D249: R | E249: 148 | F249: $18,354,356
A250: 1954470 | B250: Gangs of Wasseypur | C250: 2012 | D250: Not Rated | E250: 321 | F250: $4,384,642
A251: 1454029 | B251: The Help | C251: 2011 | D251: PG-13 | E251: 146 | F251: $169,708,112

Sheet genre
A1: MOV-ID | B1: genre
A2: 111161 | B2: Epic
A3: 111161 | B3: Period Drama
A4: 111161 | B4: Prison Drama
A5: 111161 | B5: Drama
A6: 68646 | B6: Epic
A7: 68646 | B7: Gangster
A8: 68646 | B8: Tragedy
A9: 68646 | B9: Crime
A10: 68646 | B10: Drama
A11: 468569 | B11: Action Epic
A12: 468569 | B12: Epic
A13: 468569 | B13: Superhero
... A1645: 1454029 | B1645: Drama

Sheet director
A1: MOV-ID | B1: director_ID | C1: director
A2: 111161 | B2: 1104 | C2: Frank Darabont
A3: 68646 | B3: 338 | C3: Francis Ford Coppola
A4: 468569 | B4: 634240 | C4: Christopher Nolan
A5: 71562 | B5: 338 | C5: Francis Ford Coppola
A6: 50083 | B6: 1486 | C6: Sidney Lumet
A7: 167260 | B7: 1392 | C7: Peter Jackson
A8: 108052 | B8: 229 | C8: Steven Spielberg
A9: 120737 | B9: 1392 | C9: Peter Jackson
A10: 110912 | B10: 233 | C10: Quentin Tarantino
A11: 60196 | B11: 1466 | C11: Sergio Leone
A12: 109830 | B12: 709 | C12: Robert Zemeckis
A13: 167261 | B13: 1392 | C13: Peter Jackson
... A279: 1454029 | B279: 853238 | C279: Tate Taylor

Sheet writer
A1: MOV-ID | B1: writer_ID | C1: writer
A2: 111161 | B2: 175 | C2: Stephen King
A3: 111161 | B3: 1104 | C3: Frank Darabont
A4: 68646 | B4: 701374 | C4: Mario Puzo
A5: 68646 | B5: 338 | C5: Francis Ford Coppola
A6: 468569 | B6: 634300 | C6: Jonathan Nolan
A7: 468569 | B7: 634240 | C7: Christopher Nolan
A8: 468569 | B8: 275286 | C8: David S. Goyer
A9: 71562 | B9: 338 | C9: Francis Ford Coppola
A10: 71562 | B10: 701374 | C10: Mario Puzo
A11: 50083 | B11: 741627 | C11: Reginald Rose
A12: 167260 | B12: 866058 | C12: J.R.R. Tolkien
A13: 167260 | B13: 909638 | C13: Fran Walsh
... A554: 1454029 | B554: 3543826 | C554: Kathryn Stockett

Sheet star
A1: MOV-ID | B1: star_ID | C1: star
A2: 111161 | B2: 209 | C2: Tim Robbins
A3: 111161 | B3: 151 | C3: Morgan Freeman
A4: 111161 | B4: 348409 | C4: Bob Gunton
A5: 68646 | B5: 8 | C5: Marlon Brando
A6: 68646 | B6: 199 | C6: Al Pacino
A7: 68646 | B7: 1001 | C7: James Caan
A8: 468569 | B8: 288 | C8: Christian Bale
A9: 468569 | B9: 5132 | C9: Heath Ledger
A10: 468569 | B10: 1173 | C10: Aaron Eckhart
A11: 71562 | B11: 199 | C11: Al Pacino
A12: 71562 | B12: 134 | C12: Robert De Niro
A13: 71562 | B13: 380 | C13: Robert Duvall
... A751: 1454029 | B751: 818055 | C751: Octavia Spencer

Sheet All Data
A1: MOV-ID | B1: title | C1: year | D1: parental_guide | E1: runtime | F1: gross_us_canada | G1: genre.genre | H1: director.director_ID | I1: director.director | J1: writer.writer_ID | K1: writer.writer | L1: star.star_ID | M1: star.star | N1: decade
A2: 4154796 | B2: Avengers: Endgame | C2: 2019 | D2: PG-13 | E2: 181 | F2: 858373000 | G2: Space Sci-Fi | H2: 751577 | I2: Anthony Russo | J2: 1321655 | K2: Christopher Markus | L2: 375 | M2: Robert Downey Jr. | N2: =INT(C2/10)*10 & "-" & INT(C2/10)*10+9 -> 2010-2019
A3: 4154796 | B3: Avengers: Endgame | C3: 2019 | D3: PG-13 | E3: 181 | F3: 858373000 | G3: Space Sci-Fi | H3: 751577 | I3: Anthony Russo | J3: 1321655 | K3: Christopher Markus | L3: 262635 | M3: Chris Evans | N3: =INT(C3/10)*10 & "-" & INT(C3/10)*10+9 -> 2010-2019
A4: 4154796 | B4: Avengers: Endgame | C4: 2019 | D4: PG-13 | E4: 181 | F4: 858373000 | G4: Space Sci-Fi | H4: 751577 | I4: Anthony Russo | J4: 1321655 | K4: Christopher Markus | L4: 749263 | M4: Mark Ruffalo | N4: =INT(C4/10)*10 & "-" & INT(C4/10)*10+9 -> 2010-2019
A5: 4154796 | B5: Avengers: Endgame | C5: 2019 | D5: PG-13 | E5: 181 | F5: 858373000 | G5: Space Sci-Fi | H5: 751577 | I5: Anthony Russo | J5: 1321656 | K5: Stephen McFeely | L5: 375 | M5: Robert Downey Jr. | N5: =INT(C5/10)*10 & "-" & INT(C5/10)*10+9 -> 2010-2019
A6: 4154796 | B6: Avengers: Endgame | C6: 2019 | D6: PG-13 | E6: 181 | F6: 858373000 | G6: Space Sci-Fi | H6: 751577 | I6: Anthony Russo | J6: 1321656 | K6: Stephen McFeely | L6: 262635 | M6: Chris Evans | N6: =INT(C6/10)*10 & "-" & INT(C6/10)*10+9 -> 2010-2019
A7: 4154796 | B7: Avengers: Endgame | C7: 2019 | D7: PG-13 | E7: 181 | F7: 858373000 | G7: Space Sci-Fi | H7: 751577 | I7: Anthony Russo | J7: 1321656 | K7: Stephen McFeely | L7: 749263 | M7: Mark Ruffalo | N7: =INT(C7/10)*10 & "-" & INT(C7/10)*10+9 -> 2010-2019
A8: 4154796 | B8: Avengers: Endgame | C8: 2019 | D8: PG-13 | E8: 181 | F8: 858373000 | G8: Space Sci-Fi | H8: 751577 | I8: Anthony Russo | J8: 498278 | K8: Stan Lee | L8: 375 | M8: Robert Downey Jr. | N8: =INT(C8/10)*10 & "-" & INT(C8/10)*10+9 -> 2010-2019
A9: 4154796 | B9: Avengers: Endgame | C9: 2019 | D9: PG-13 | E9: 181 | F9: 858373000 | G9: Space Sci-Fi | H9: 751577 | I9: Anthony Russo | J9: 498278 | K9: Stan Lee | L9: 262635 | M9: Chris Evans | N9: =INT(C9/10)*10 & "-" & INT(C9/10)*10+9 -> 2010-2019
A10: 4154796 | B10: Avengers: Endgame | C10: 2019 | D10: PG-13 | E10: 181 | F10: 858373000 | G10: Space Sci-Fi | H10: 751577 | I10: Anthony Russo | J10: 498278 | K10: Stan Lee | L10: 749263 | M10: Mark Ruffalo | N10: =INT(C10/10)*10 & "-" & INT(C10/10)*10+9 -> 2010-2019
A11: 4154796 | B11: Avengers: Endgame | C11: 2019 | D11: PG-13 | E11: 181 | F11: 858373000 | G11: Space Sci-Fi | H11: 751648 | I11: Joe Russo | J11: 1321655 | K11: Christopher Markus | L11: 375 | M11: Robert Downey Jr. | N11: =INT(C11/10)*10 & "-" & INT(C11/10)*10+9 -> 2010-2019
A12: 4154796 | B12: Avengers: Endgame | C12: 2019 | D12: PG-13 | E12: 181 | F12: 858373000 | G12: Space Sci-Fi | H12: 751648 | I12: Joe Russo | J12: 1321655 | K12: Christopher Markus | L12: 262635 | M12: Chris Evans | N12: =INT(C12/10)*10 & "-" & INT(C12/10)*10+9 -> 2010-2019
A13: 4154796 | B13: Avengers: Endgame | C13: 2019 | D13: PG-13 | E13: 181 | F13: 858373000 | G13: Space Sci-Fi | H13: 751648 | I13: Joe Russo | J13: 1321655 | K13: Christopher Markus | L13: 749263 | M13: Mark Ruffalo | N13: =INT(C13/10)*10 & "-" & INT(C13/10)*10+9 -> 2010-2019
... A9205: 119698 | B9205: Princess Mononoke | C9205: 1997 | D9205: PG-13 | E9205: 133 | F9205: 11696687 | G9205: Supernatural Fantasy | H9205: 594503 | I9205: Hayao Miyazaki | J9205: 594503 | K9205: Hayao Miyazaki | L9205: 849100 | M9205: Yûko Tanaka | N9205: =INT(C9205/10)*10 & "-" & INT(C9205/10)*10+9 -> 1990-1999
A9206: 82096 | B9206: Das Boot | C9206: 1981 | E9206: 149 | F9206: 11487676 | G9206: Epic | H9206: 583 | I9206: Wolfgang Petersen | J9206: 583 | K9206: Wolfgang Petersen | L9206: 1638 | M9206: Jürgen Prochnow | N9206: =INT(C9206/10)*10 & "-" & INT(C9206/10)*10+9 -> 1980-1989
A9207: 82096 | B9207: Das Boot | C9207: 1981 | E9207: 149 | F9207: 11487676 | G9207: Epic | H9207: 583 | I9207: Wolfgang Petersen | J9207: 583 | K9207: Wolfgang Petersen | L9207: 344963 | M9207: Herbert Grönemeyer | N9207: =INT(C9207/10)*10 & "-" & INT(C9207/10)*10+9 -> 1980-1989
A9208: 82096 | B9208: Das Boot | C9208: 1981 | E9208: 149 | F9208: 11487676 | G9208: Epic | H9208: 583 | I9208: Wolfgang Petersen | J9208: 583 | K9208: Wolfgang Petersen | L9208: 921044 | M9208: Klaus Wennemann | N9208: =INT(C9208/10)*10 & "-" & INT(C9208/10)*10+9 -> 1980-1989
A9209: 82096 | B9209: Das Boot | C9209: 1981 | E9209: 149 | F9209: 11487676 | G9209: Epic | H9209: 583 | I9209: Wolfgang Petersen | J9209: 118164 | K9209: Lothar G. Buchheim | L9209: 1638 | M9209: Jürgen Prochnow | N9209: =INT(C9209/10)*10 & "-" & INT(C9209/10)*10+9 -> 1980-1989
A9210: 82096 | B9210: Das Boot | C9210: 1981 | E9210: 149 | F9210: 11487676 | G9210: Epic | H9210: 583 | I9210: Wolfgang Petersen | J9210: 118164 | K9210: Lothar G. Buchheim | L9210: 344963 | M9210: Herbert Grönemeyer | N9210: =INT(C9210/10)*10 & "-" & INT(C9210/10)*10+9 -> 1980-1989
A9211: 82096 | B9211: Das Boot | C9211: 1981 | E9211: 149 | F9211: 11487676 | G9211: Epic | H9211: 583 | I9211: Wolfgang Petersen | J9211: 118164 | K9211: Lothar G. Buchheim | L9211: 921044 | M9211: Klaus Wennemann | N9211: =INT(C9211/10)*10 & "-" & INT(C9211/10)*10+9 -> 1980-1989
A9212: 82096 | B9212: Das Boot | C9212: 1981 | E9212: 149 | F9212: 11487676 | G9212: War Epic | H9212: 583 | I9212: Wolfgang Petersen | J9212: 583 | K9212: Wolfgang Petersen | L9212: 1638 | M9212: Jürgen Prochnow | N9212: =INT(C9212/10)*10 & "-" & INT(C9212/10)*10+9 -> 1980-1989
A9213: 82096 | B9213: Das Boot | C9213: 1981 | E9213: 149 | F9213: 11487676 | G9213: War Epic | H9213: 583 | I9213: Wolfgang Petersen | J9213: 583 | K9213: Wolfgang Petersen | L9213: 344963 | M9213: Herbert Grönemeyer | N9213: =INT(C9213/10)*10 & "-" & INT(C9213/10)*10+9 -> 1980-1989
A9214: 82096 | B9214: Das Boot | C9214: 1981 | E9214: 149 | F9214: 11487676 | G9214: War Epic | H9214: 583 | I9214: Wolfgang Petersen | J9214: 583 | K9214: Wolfgang Petersen | L9214: 921044 | M9214: Klaus Wennemann | N9214: =INT(C9214/10)*10 & "-" & INT(C9214/10)*10+9 -> 1980-1989
A9215: 82096 | B9215: Das Boot | C9215: 1981 | E9215: 149 | F9215: 11487676 | G9215: War Epic | H9215: 583 | I9215: Wolfgang Petersen | J9215: 118164 | K9215: Lothar G. Buchheim | L9215: 1638 | M9215: Jürgen Prochnow | N9215: =INT(C9215/10)*10 & "-" & INT(C9215/10)*10+9 -> 1980-1989
A9216: 82096 | B9216: Das Boot | C9216: 1981 | E9216: 149 | F9216: 11487676 | G9216: War Epic | H9216: 583 | I9216: Wolfgang Petersen | J9216: 118164 | K9216: Lothar G. Buchheim | L9216: 344963 | M9216: Herbert Grönemeyer | N9216: =INT(C9216/10)*10 & "-" & INT(C9216/10)*10+9 -> 1980-1989
A9217: 82096 | B9217: Das Boot | C9217: 1981 | E9217: 149 | F9217: 11487676 | G9217: War Epic | H9217: 583 | I9217: Wolfgang Petersen | J9217: 118164 | K9217: Lothar G. Buchheim | L9217: 921044 | M9217: Klaus Wennemann | N9217: =INT(C9217/10)*10 & "-" & INT(C9217/10)*10+9 -> 1980-1989
... A9229: 82096 | B9229: Das Boot | C9229: 1981 | E9229: 149 | F9229: 11487676 | G9229: War | H9229: 583 | I9229: Wolfgang Petersen | J9229: 118164 | K9229: Lothar G. Buchheim | L9229: 921044 | M9229: Klaus Wennemann | N9229: =INT(C9229/10)*10 & "-" & INT(C9229/10)*10+9 -> 1980-1989
A9230: 405094 | B9230: The Lives of Others | C9230: 2006 | D9230: R | E9230: 137 | F9230: 11286112 | G9230: Political Thriller | H9230: 3697 | I9230: Florian Henckel von Donnersmarck | J9230: 3697 | K9230: Florian Henckel von Donnersmarck | L9230: 618057 | M9230: Ulrich Mühe | N9230: =INT(C9230/10)*10 & "-" & INT(C9230/10)*10+9 -> 2000-2009
A9231: 405094 | B9231: The Lives of Others | C9231: 2006 | D9231: R | E9231: 137 | F9231: 11286112 | G9231: Political Thriller | H9231: 3697 | I9231: Florian Henckel von Donnersmarck | J9231: 3697 | K9231: Florian Henckel von Donnersmarck | L9231: 311476 | M9231: Martina Gedeck | N9231: =INT(C9231/10)*10 & "-" & INT(C9231/10)*10+9 -> 2000-2009
A9232: 405094 | B9232: The Lives of Others | C9232: 2006 | D9232: R | E9232: 137 | F9232: 11286112 | G9232: Political Thriller | H9232: 3697 | I9232: Florian Henckel von Donnersmarck | J9232: 3697 | K9232: Florian Henckel von Donnersmarck | L9232: 462407 | M9232: Sebastian Koch | N9232: =INT(C9232/10)*10 & "-" & INT(C9232/10)*10+9 -> 2000-2009
A9233: 405094 | B9233: The Lives of Others | C9233: 2006 | D9233: R | E9233: 137 | F9233: 11286112 | G9233: Psychological Drama | H9233: 3697 | I9233: Florian Henckel von Donnersmarck | J9233: 3697 | K9233: Florian Henckel von Donnersmarck | L9233: 618057 | M9233: Ulrich Mühe | N9233: =INT(C9233/10)*10 & "-" & INT(C9233/10)*10+9 -> 2000-2009
A9234: 405094 | B9234: The Lives of Others | C9234: 2006 | D9234: R | E9234: 137 | F9234: 11286112 | G9234: Psychological Drama | H9234: 3697 | I9234: Florian Henckel von Donnersmarck | J9234: 3697 | K9234: Florian Henckel von Donnersmarck | L9234: 311476 | M9234: Martina Gedeck | N9234: =INT(C9234/10)*10 & "-" & INT(C9234/10)*10+9 -> 2000-2009
A9235: 405094 | B9235: The Lives of Others | C9235: 2006 | D9235: R | E9235: 137 | F9235: 11286112 | G9235: Psychological Drama | H9235: 3697 | I9235: Florian Henckel von Donnersmarck | J9235: 3697 | K9235: Florian Henckel von Donnersmarck | L9235: 462407 | M9235: Sebastian Koch | N9235: =INT(C9235/10)*10 & "-" & INT(C9235/10)*10+9 -> 2000-2009
A9236: 405094 | B9236: The Lives of Others | C9236: 2006 | D9236: R | E9236: 137 | F9236: 11286112 | G9236: Spy | H9236: 3697 | I9236: Florian Henckel von Donnersmarck | J9236: 3697 | K9236: Florian Henckel von Donnersmarck | L9236: 618057 | M9236: Ulrich Mühe | N9236: =INT(C9236/10)*10 & "-" & INT(C9236/10)*10+9 -> 2000-2009
A9237: 405094 | B9237: The Lives of Others | C9237: 2006 | D9237: R | E9237: 137 | F9237: 11286112 | G9237: Spy | H9237: 3697 | I9237: Florian Henckel von Donnersmarck | J9237: 3697 | K9237: Florian Henckel von Donnersmarck | L9237: 311476 | M9237: Martina Gedeck | N9237: =INT(C9237/10)*10 & "-" & INT(C9237/10)*10+9 -> 2000-2009
A9238: 405094 | B9238: The Lives of Others | C9238: 2006 | D9238: R | E9238: 137 | F9238: 11286112 | G9238: Spy | H9238: 3697 | I9238: Florian Henckel von Donnersmarck | J9238: 3697 | K9238: Florian Henckel von Donnersmarck | L9238: 462407 | M9238: Sebastian Koch | N9238: =INT(C9238/10)*10 & "-" & INT(C9238/10)*10+9 -> 2000-2009
A9239: 405094 | B9239: The Lives of Others | C9239: 2006 | D9239: R | E9239: 137 | F9239: 11286112 | G9239: Drama | H9239: 3697 | I9239: Florian Henckel von Donnersmarck | J9239: 3697 | K9239: Florian Henckel von Donnersmarck | L9239: 618057 | M9239: Ulrich Mühe | N9239: =INT(C9239/10)*10 & "-" & INT(C9239/10)*10+9 -> 2000-2009
A9240: 405094 | B9240: The Lives of Others | C9240: 2006 | D9240: R | E9240: 137 | F9240: 11286112 | G9240: Drama | H9240: 3697 | I9240: Florian Henckel von Donnersmarck | J9240: 3697 | K9240: Florian Henckel von Donnersmarck | L9240: 311476 | M9240: Martina Gedeck | N9240: =INT(C9240/10)*10 & "-" & INT(C9240/10)*10+9 -> 2000-2009
A9241: 405094 | B9241: The Lives of Others | C9241: 2006 | D9241: R | E9241: 137 | F9241: 11286112 | G9241: Drama | H9241: 3697 | I9241: Florian Henckel von Donnersmarck | J9241: 3697 | K9241: Florian Henckel von Donnersmarck | L9241: 462407 | M9241: Sebastian Koch | N9241: =INT(C9241/10)*10 & "-" & INT(C9241/10)*10+9 -> 2000-2009
... A9988: 87843 | B9988: Once Upon a Time in America | C9988: 1984 | D9988: R | E9988: 229 | F9988: 5321508 | G9988: Drama | H9988: 1466 | I9988: Sergio Leone | J9988: 207401 | K9988: Piero De Bernardi | L9988: 1527 | M9988: Elizabeth McGovern | N9988: =INT(C9988/10)*10 & "-" & INT(C9988/10)*10+9 -> 1980-1989
A9989: 5311514 | B9989: Your Name. | C9989: 2016 | E9989: 106 | F9989: 5017246 | G9989: Anime | H9989: 1396121 | I9989: Makoto Shinkai | J9989: 1396121 | K9989: Makoto Shinkai | L9989: 1126340 | M9989: Ryûnosuke Kamiki | N9989: =INT(C9989/10)*10 & "-" & INT(C9989/10)*10+9 -> 2010-2019
A9990: 5311514 | B9990: Your Name. | C9990: 2016 | E9990: 106 | F9990: 5017246 | G9990: Anime | H9990: 1396121 | I9990: Makoto Shinkai | J9990: 1396121 | K9990: Makoto Shinkai | L9990: 4759838 | M9990: Mone Kamishiraishi | N9990: =INT(C9990/10)*10 & "-" & INT(C9990/10)*10+9 -> 2010-2019
A9991: 5311514 | B9991: Your Name. | C9991: 2016 | E9991: 106 | F9991: 5017246 | G9991: Anime | H9991: 1396121 | I9991: Makoto Shinkai | J9991: 1396121 | K9991: Makoto Shinkai | L9991: 6954008 | M9991: Ryo Narita | N9991: =INT(C9991/10)*10 & "-" & INT(C9991/10)*10+9 -> 2010-2019
A9992: 5311514 | B9992: Your Name. | C9992: 2016 | E9992: 106 | F9992: 5017246 | G9992: Hand-Drawn Animation | H9992: 1396121 | I9992: Makoto Shinkai | J9992: 1396121 | K9992: Makoto Shinkai | L9992: 1126340 | M9992: Ryûnosuke Kamiki | N9992: =INT(C9992/10)*10 & "-" & INT(C9992/10)*10+9 -> 2010-2019
A9993: 5311514 | B9993: Your Name. | C9993: 2016 | E9993: 106 | F9993: 5017246 | G9993: Hand-Drawn Animation | H9993: 1396121 | I9993: Makoto Shinkai | J9993: 1396121 | K9993: Makoto Shinkai | L9993: 4759838 | M9993: Mone Kamishiraishi | N9993: =INT(C9993/10)*10 & "-" & INT(C9993/10)*10+9 -> 2010-2019
A9994: 5311514 | B9994: Your Name. | C9994: 2016 | E9994: 106 | F9994: 5017246 | G9994: Hand-Drawn Animation | H9994: 1396121 | I9994: Makoto Shinkai | J9994: 1396121 | K9994: Makoto Shinkai | L9994: 6954008 | M9994: Ryo Narita | N9994: =INT(C9994/10)*10 & "-" & INT(C9994/10)*10+9 -> 2010-2019
A9995: 5311514 | B9995: Your Name. | C9995: 2016 | E9995: 106 | F9995: 5017246 | G9995: Psychological Drama | H9995: 1396121 | I9995: Makoto Shinkai | J9995: 1396121 | K9995: Makoto Shinkai | L9995: 1126340 | M9995: Ryûnosuke Kamiki | N9995: =INT(C9995/10)*10 & "-" & INT(C9995/10)*10+9 -> 2010-2019
A9996: 5311514 | B9996: Your Name. | C9996: 2016 | E9996: 106 | F9996: 5017246 | G9996: Psychological Drama | H9996: 1396121 | I9996: Makoto Shinkai | J9996: 1396121 | K9996: Makoto Shinkai | L9996: 4759838 | M9996: Mone Kamishiraishi | N9996: =INT(C9996/10)*10 & "-" & INT(C9996/10)*10+9 -> 2010-2019
A9997: 5311514 | B9997: Your Name. | C9997: 2016 | E9997: 106 | F9997: 5017246 | G9997: Psychological Drama | H9997: 1396121 | I9997: Makoto Shinkai | J9997: 1396121 | K9997: Makoto Shinkai | L9997: 6954008 | M9997: Ryo Narita | N9997: =INT(C9997/10)*10 & "-" & INT(C9997/10)*10+9 -> 2010-2019
A9998: 5311514 | B9998: Your Name. | C9998: 2016 | E9998: 106 | F9998: 5017246 | G9998: Shōjo | H9998: 1396121 | I9998: Makoto Shinkai | J9998: 1396121 | K9998: Makoto Shinkai | L9998: 1126340 | M9998: Ryûnosuke Kamiki | N9998: =INT(C9998/10)*10 & "-" & INT(C9998/10)*10+9 -> 2010-2019
A9999: 5311514 | B9999: Your Name. | C9999: 2016 | E9999: 106 | F9999: 5017246 | G9999: Shōjo | H9999: 1396121 | I9999: Makoto Shinkai | J9999: 1396121 | K9999: Makoto Shinkai | L9999: 4759838 | M9999: Mone Kamishiraishi | N9999: =INT(C9999/10)*10 & "-" & INT(C9999/10)*10+9 -> 2010-2019
A10000: 5311514 | B10000: Your Name. | C10000: 2016 | E10000: 106 | F10000: 5017246 | G10000: Shōjo | H10000: 1396121 | I10000: Makoto Shinkai | J10000: 1396121 | K10000: Makoto Shinkai | L10000: 6954008 | M10000: Ryo Narita | N10000: =INT(C10000/10)*10 & "-" & INT(C10000/10)*10+9 -> 2010-2019
... A10012: 5311514 | B10012: Your Name. | C10012: 2016 | E10012: 106 | F10012: 5017246 | G10012: Romance | H10012: 1396121 | I10012: Makoto Shinkai | J10012: 1396121 | K10012: Makoto Shinkai | L10012: 6954008 | M10012: Ryo Narita | N10012: =INT(C10012/10)*10 & "-" & INT(C10012/10)*10+9 -> 2010-2019
A10013: 40897 | B10013: The Treasure of the Sierra Madre | C10013: 1948 | D10013: Approved | E10013: 126 | F10013: 5014000 | G10013: Tragedy | H10013: 1379 | I10013: John Huston | J10013: 1379 | K10013: John Huston | L10013: 7 | M10013: Humphrey Bogart | N10013: =INT(C10013/10)*10 & "-" & INT(C10013/10)*10+9 -> 1940-1949
A10014: 40897 | B10014: The Treasure of the Sierra Madre | C10014: 1948 | D10014: Approved | E10014: 126 | F10014: 5014000 | G10014: Tragedy | H10014: 1379 | I10014: John Huston | J10014: 1379 | K10014: John Huston | L10014: 404158 | M10014: Walter Huston | N10014: =INT(C10014/10)*10 & "-" & INT(C10014/10)*10+9 -> 1940-1949
A10015: 40897 | B10015: The Treasure of the Sierra Madre | C10015: 1948 | D10015: Approved | E10015: 126 | F10015: 5014000 | G10015: Tragedy | H10015: 1379 | I10015: John Huston | J10015: 1379 | K10015: John Huston | L10015: 392529 | M10015: Tim Holt | N10015: =INT(C10015/10)*10 & "-" & INT(C10015/10)*10+9 -> 1940-1949
A10016: 40897 | B10016: The Treasure of the Sierra Madre | C10016: 1948 | D10016: Approved | E10016: 126 | F10016: 5014000 | G10016: Tragedy | H10016: 1379 | I10016: John Huston | J10016: 871252 | K10016: B. Traven | L10016: 7 | M10016: Humphrey Bogart | N10016: =INT(C10016/10)*10 & "-" & INT(C10016/10)*10+9 -> 1940-1949
A10017: 40897 | B10017: The Treasure of the Sierra Madre | C10017: 1948 | D10017: Approved | E10017: 126 | F10017: 5014000 | G10017: Tragedy | H10017: 1379 | I10017: John Huston | J10017: 871252 | K10017: B. Traven | L10017: 404158 | M10017: Walter Huston | N10017: =INT(C10017/10)*10 & "-" & INT(C10017/10)*10+9 -> 1940-1949
A10018: 40897 | B10018: The Treasure of the Sierra Madre | C10018: 1948 | D10018: Approved | E10018: 126 | F10018: 5014000 | G10018: Tragedy | H10018: 1379 | I10018: John Huston | J10018: 871252 | K10018: B. Traven | L10018: 392529 | M10018: Tim Holt | N10018: =INT(C10018/10)*10 & "-" & INT(C10018/10)*10+9 -> 1940-1949
A10019: 40897 | B10019: The Treasure of the Sierra Madre | C10019: 1948 | D10019: Approved | E10019: 126 | F10019: 5014000 | G10019: Adventure | H10019: 1379 | I10019: John Huston | J10019: 1379 | K10019: John Huston | L10019: 7 | M10019: Humphrey Bogart | N10019: =INT(C10019/10)*10 & "-" & INT(C10019/10)*10+9 -> 1940-1949
A10020: 40897 | B10020: The Treasure of the Sierra Madre | C10020: 1948 | D10020: Approved | E10020: 126 | F10020: 5014000 | G10020: Adventure | H10020: 1379 | I10020: John Huston | J10020: 1379 | K10020: John Huston | L10020: 404158 | M10020: Walter Huston | N10020: =INT(C10020/10)*10 & "-" & INT(C10020/10)*10+9 -> 1940-1949
A10021: 40897 | B10021: The Treasure of the Sierra Madre | C10021: 1948 | D10021: Approved | E10021: 126 | F10021: 5014000 | G10021: Adventure | H10021: 1379 | I10021: John Huston | J10021: 1379 | K10021: John Huston | L10021: 392529 | M10021: Tim Holt | N10021: =INT(C10021/10)*10 & "-" & INT(C10021/10)*10+9 -> 1940-1949
A10022: 40897 | B10022: The Treasure of the Sierra Madre | C10022: 1948 | D10022: Approved | E10022: 126 | F10022: 5014000 | G10022: Adventure | H10022: 1379 | I10022: John Huston | J10022: 871252 | K10022: B. Traven | L10022: 7 | M10022: Humphrey Bogart | N10022: =INT(C10022/10)*10 & "-" & INT(C10022/10)*10+9 -> 1940-1949
A10023: 40897 | B10023: The Treasure of the Sierra Madre | C10023: 1948 | D10023: Approved | E10023: 126 | F10023: 5014000 | G10023: Adventure | H10023: 1379 | I10023: John Huston | J10023: 871252 | K10023: B. Traven | L10023: 404158 | M10023: Walter Huston | N10023: =INT(C10023/10)*10 & "-" & INT(C10023/10)*10+9 -> 1940-1949
A10024: 40897 | B10024: The Treasure of the Sierra Madre | C10024: 1948 | D10024: Approved | E10024: 126 | F10024: 5014000 | G10024: Adventure | H10024: 1379 | I10024: John Huston | J10024: 871252 | K10024: B. Traven | L10024: 392529 | M10024: Tim Holt | N10024: =INT(C10024/10)*10 & "-" & INT(C10024/10)*10+9 -> 1940-1949
... A11071: 17136 | B11071: Metropolis | C11071: 1927 | D11071: Not Rated | E11071: 153 | F11071: 1236166 | G11071: Sci-Fi | H11071: 485 | I11071: Fritz Lang | J11071: 485 | K11071: Fritz Lang | L11071: 297054 | M11071: Gustav Fröhlich | N11071: =INT(C11071/10)*10 & "-" & INT(C11071/10)*10+9 -> 1920-1929
A11072: 26548265 | B11072: Maharaja | C11072: 2024 | E11072: 141 | F11072: 975543 | G11072: One-Person Army Action | H11072: 9204865 | I11072: Nithilan Saminathan | J11072: 9204865 | K11072: Nithilan Saminathan | L11072: 4043111 | M11072: Vijay Sethupathi | N11072: =INT(C11072/10)*10 & "-" & INT(C11072/10)*10+9 -> 2020-2029
A11073: 26548265 | B11073: Maharaja | C11073: 2024 | E11073: 141 | F11073: 975543 | G11073: One-Person Army Action | H11073: 9204865 | I11073: Nithilan Saminathan | J11073: 9204865 | K11073: Nithilan Saminathan | L11073: 440604 | M11073: Anurag Kashyap | N11073: =INT(C11073/10)*10 & "-" & INT(C11073/10)*10+9 -> 2020-2029
A11074: 26548265 | B11074: Maharaja | C11074: 2024 | E11074: 141 | F11074: 975543 | G11074: One-Person Army Action | H11074: 9204865 | I11074: Nithilan Saminathan | J11074: 9204865 | K11074: Nithilan Saminathan | L11074: 1952830 | M11074: Mamta Mohandas | N11074: =INT(C11074/10)*10 & "-" & INT(C11074/10)*10+9 -> 2020-2029
A11075: 26548265 | B11075: Maharaja | C11075: 2024 | E11075: 141 | F11075: 975543 | G11075: Action | H11075: 9204865 | I11075: Nithilan Saminathan | J11075: 9204865 | K11075: Nithilan Saminathan | L11075: 4043111 | M11075: Vijay Sethupathi | N11075: =INT(C11075/10)*10 & "-" & INT(C11075/10)*10+9 -> 2020-2029
A11076: 26548265 | B11076: Maharaja | C11076: 2024 | E11076: 141 | F11076: 975543 | G11076: Action | H11076: 9204865 | I11076: Nithilan Saminathan | J11076: 9204865 | K11076: Nithilan Saminathan | L11076: 440604 | M11076: Anurag Kashyap | N11076: =INT(C11076/10)*10 & "-" & INT(C11076/10)*10+9 -> 2020-2029
A11077: 26548265 | B11077: Maharaja | C11077: 2024 | E11077: 141 | F11077: 975543 | G11077: Action | H11077: 9204865 | I11077: Nithilan Saminathan | J11077: 9204865 | K11077: Nithilan Saminathan | L11077: 1952830 | M11077: Mamta Mohandas | N11077: =INT(C11077/10)*10 & "-" & INT(C11077/10)*10+9 -> 2020-2029
A11078: 26548265 | B11078: Maharaja | C11078: 2024 | E11078: 141 | F11078: 975543 | G11078: Crime | H11078: 9204865 | I11078: Nithilan Saminathan | J11078: 9204865 | K11078: Nithilan Saminathan | L11078: 4043111 | M11078: Vijay Sethupathi | N11078: =INT(C11078/10)*10 & "-" & INT(C11078/10)*10+9 -> 2020-2029
A11079: 26548265 | B11079: Maharaja | C11079: 2024 | E11079: 141 | F11079: 975543 | G11079: Crime | H11079: 9204865 | I11079: Nithilan Saminathan | J11079: 9204865 | K11079: Nithilan Saminathan | L11079: 440604 | M11079: Anurag Kashyap | N11079: =INT(C11079/10)*10 & "-" & INT(C11079/10)*10+9 -> 2020-2029
A11080: 26548265 | B11080: Maharaja | C11080: 2024 | E11080: 141 | F11080: 975543 | G11080: Crime | H11080: 9204865 | I11080: Nithilan Saminathan | J11080: 9204865 | K11080: Nithilan Saminathan | L11080: 1952830 | M11080: Mamta Mohandas | N11080: =INT(C11080/10)*10 & "-" & INT(C11080/10)*10+9 -> 2020-2029
A11081: 26548265 | B11081: Maharaja | C11081: 2024 | E11081: 141 | F11081: 975543 | G11081: Drama | H11081: 9204865 | I11081: Nithilan Saminathan | J11081: 9204865 | K11081: Nithilan Saminathan | L11081: 4043111 | M11081: Vijay Sethupathi | N11081: =INT(C11081/10)*10 & "-" & INT(C11081/10)*10+9 -> 2020-2029
A11082: 26548265 | B11082: Maharaja | C11082: 2024 | E11082: 141 | F11082: 975543 | G11082: Drama | H11082: 9204865 | I11082: Nithilan Saminathan | J11082: 9204865 | K11082: Nithilan Saminathan | L11082: 440604 | M11082: Anurag Kashyap | N11082: =INT(C11082/10)*10 & "-" & INT(C11082/10)*10+9 -> 2020-2029
A11083: 26548265 | B11083: Maharaja | C11083: 2024 | E11083: 141 | F11083: 975543 | G11083: Drama | H11083: 9204865 | I11083: Nithilan Saminathan | J11083: 9204865 | K11083: Nithilan Saminathan | L11083: 1952830 | M11083: Mamta Mohandas | N11083: =INT(C11083/10)*10 & "-" & INT(C11083/10)*10+9 -> 2020-2029
... A11086: 26548265 | B11086: Maharaja | C11086: 2024 | E11086: 141 | F11086: 975543 | G11086: Thriller | H11086: 9204865 | I11086: Nithilan Saminathan | J11086: 9204865 | K11086: Nithilan Saminathan | L11086: 1952830 | M11086: Mamta Mohandas | N11086: =INT(C11086/10)*10 & "-" & INT(C11086/10)*10+9 -> 2020-2029
A11087: 32553 | B11087: The Great Dictator | C11087: 1940 | D11087: G | E11087: 125 | F11087: 972212 | G11087: Dark Comedy | H11087: 122 | I11087: Charles Chaplin | J11087: 122 | K11087: Charles Chaplin | L11087: 122 | M11087: Charles Chaplin | N11087: =INT(C11087/10)*10 & "-" & INT(C11087/10)*10+9 -> 1940-1949
A11088: 32553 | B11088: The Great Dictator | C11088: 1940 | D11088: G | E11088: 125 | F11088: 972212 | G11088: Dark Comedy | H11088: 122 | I11088: Charles Chaplin | J11088: 122 | K11088: Charles Chaplin | L11088: 2104 | M11088: Paulette Goddard | N11088: =INT(C11088/10)*10 & "-" & INT(C11088/10)*10+9 -> 1940-1949
A11089: 32553 | B11089: The Great Dictator | C11089: 1940 | D11089: G | E11089: 125 | F11089: 972212 | G11089: Dark Comedy | H11089: 122 | I11089: Charles Chaplin | J11089: 122 | K11089: Charles Chaplin | L11089: 642988 | M11089: Jack Oakie | N11089: =INT(C11089/10)*10 & "-" & INT(C11089/10)*10+9 -> 1940-1949
A11090: 32553 | B11090: The Great Dictator | C11090: 1940 | D11090: G | E11090: 125 | F11090: 972212 | G11090: Parody | H11090: 122 | I11090: Charles Chaplin | J11090: 122 | K11090: Charles Chaplin | L11090: 122 | M11090: Charles Chaplin | N11090: =INT(C11090/10)*10 & "-" & INT(C11090/10)*10+9 -> 1940-1949
A11091: 32553 | B11091: The Great Dictator | C11091: 1940 | D11091: G | E11091: 125 | F11091: 972212 | G11091: Parody | H11091: 122 | I11091: Charles Chaplin | J11091: 122 | K11091: Charles Chaplin | L11091: 2104 | M11091: Paulette Goddard | N11091: =INT(C11091/10)*10 & "-" & INT(C11091/10)*10+9 -> 1940-1949
A11092: 32553 | B11092: The Great Dictator | C11092: 1940 | D11092: G | E11092: 125 | F11092: 972212 | G11092: Parody | H11092: 122 | I11092: Charles Chaplin | J11092: 122 | K11092: Charles Chaplin | L11092: 642988 | M11092: Jack Oakie | N11092: =INT(C11092/10)*10 & "-" & INT(C11092/10)*10+9 -> 1940-1949
A11093: 32553 | B11093: The Great Dictator | C11093: 1940 | D11093: G | E11093: 125 | F11093: 972212 | G11093: Political Drama | H11093: 122 | I11093: Charles Chaplin | J11093: 122 | K11093: Charles Chaplin | L11093: 122 | M11093: Charles Chaplin | N11093: =INT(C11093/10)*10 & "-" & INT(C11093/10)*10+9 -> 1940-1949
A11094: 32553 | B11094: The Great Dictator | C11094: 1940 | D11094: G | E11094: 125 | F11094: 972212 | G11094: Political Drama | H11094: 122 | I11094: Charles Chaplin | J11094: 122 | K11094: Charles Chaplin | L11094: 2104 | M11094: Paulette Goddard | N11094: =INT(C11094/10)*10 & "-" & INT(C11094/10)*10+9 -> 1940-1949
A11095: 32553 | B11095: The Great Dictator | C11095: 1940 | D11095: G | E11095: 125 | F11095: 972212 | G11095: Political Drama | H11095: 122 | I11095: Charles Chaplin | J11095: 122 | K11095: Charles Chaplin | L11095: 642988 | M11095: Jack Oakie | N11095: =INT(C11095/10)*10 & "-" & INT(C11095/10)*10+9 -> 1940-1949
A11096: 32553 | B11096: The Great Dictator | C11096: 1940 | D11096: G | E11096: 125 | F11096: 972212 | G11096: Satire | H11096: 122 | I11096: Charles Chaplin | J11096: 122 | K11096: Charles Chaplin | L11096: 122 | M11096: Charles Chaplin | N11096: =INT(C11096/10)*10 & "-" & INT(C11096/10)*10+9 -> 1940-1949
A11097: 32553 | B11097: The Great Dictator | C11097: 1940 | D11097: G | E11097: 125 | F11097: 972212 | G11097: Satire | H11097: 122 | I11097: Charles Chaplin | J11097: 122 | K11097: Charles Chaplin | L11097: 2104 | M11097: Paulette Goddard | N11097: =INT(C11097/10)*10 & "-" & INT(C11097/10)*10+9 -> 1940-1949
A11098: 32553 | B11098: The Great Dictator | C11098: 1940 | D11098: G | E11098: 125 | F11098: 972212 | G11098: Satire | H11098: 122 | I11098: Charles Chaplin | J11098: 122 | K11098: Charles Chaplin | L11098: 642988 | M11098: Jack Oakie | N11098: =INT(C11098/10)*10 & "-" & INT(C11098/10)*10+9 -> 1940-1949
... A12793: 17925 | B12793: The General | C12793: 1926 | D12793: Passed | E12793: 78 | F12793: 1388 | G12793: War | H12793: 36 | I12793: Buster Keaton | J12793: 90213 | K12793: Al Boasberg | L12793: 147070 | M12793: Glen Cavender | N12793: =INT(C12793/10)*10 & "-" & INT(C12793/10)*10+9 -> 1920-1929
A12794: 56058 | B12794: Harakiri | C12794: 1962 | D12794: Not Rated | E12794: 133 | G12794: Period Drama | H12794: 462030 | I12794: Masaki Kobayashi | J12794: 847668 | K12794: Yasuhiko Takiguchi | L12794: 619938 | M12794: Tatsuya Nakadai | N12794: =INT(C12794/10)*10 & "-" & INT(C12794/10)*10+9 -> 1960-1969
A12795: 56058 | B12795: Harakiri | C12795: 1962 | D12795: Not Rated | E12795: 133 | G12795: Period Drama | H12795: 462030 | I12795: Masaki Kobayashi | J12795: 847668 | K12795: Yasuhiko Takiguchi | L12795: 410968 | M12795: Akira Ishihama | N12795: =INT(C12795/10)*10 & "-" & INT(C12795/10)*10+9 -> 1960-1969
A12796: 56058 | B12796: Harakiri | C12796: 1962 | D12796: Not Rated | E12796: 133 | G12796: Period Drama | H12796: 462030 | I12796: Masaki Kobayashi | J12796: 847668 | K12796: Yasuhiko Takiguchi | L12796: 412615 | M12796: Shima Iwashita | N12796: =INT(C12796/10)*10 & "-" & INT(C12796/10)*10+9 -> 1960-1969
A12797: 56058 | B12797: Harakiri | C12797: 1962 | D12797: Not Rated | E12797: 133 | G12797: Period Drama | H12797: 462030 | I12797: Masaki Kobayashi | J12797: 368074 | K12797: Shinobu Hashimoto | L12797: 619938 | M12797: Tatsuya Nakadai | N12797: =INT(C12797/10)*10 & "-" & INT(C12797/10)*10+9 -> 1960-1969
A12798: 56058 | B12798: Harakiri | C12798: 1962 | D12798: Not Rated | E12798: 133 | G12798: Period Drama | H12798: 462030 | I12798: Masaki Kobayashi | J12798: 368074 | K12798: Shinobu Hashimoto | L12798: 410968 | M12798: Akira Ishihama | N12798: =INT(C12798/10)*10 & "-" & INT(C12798/10)*10+9 -> 1960-1969
A12799: 56058 | B12799: Harakiri | C12799: 1962 | D12799: Not Rated | E12799: 133 | G12799: Period Drama | H12799: 462030 | I12799: Masaki Kobayashi | J12799: 368074 | K12799: Shinobu Hashimoto | L12799: 412615 | M12799: Shima Iwashita | N12799: =INT(C12799/10)*10 & "-" & INT(C12799/10)*10+9 -> 1960-1969
A12800: 56058 | B12800: Harakiri | C12800: 1962 | D12800: Not Rated | E12800: 133 | G12800: Drama | H12800: 462030 | I12800: Masaki Kobayashi | J12800: 847668 | K12800: Yasuhiko Takiguchi | L12800: 619938 | M12800: Tatsuya Nakadai | N12800: =INT(C12800/10)*10 & "-" & INT(C12800/10)*10+9 -> 1960-1969
A12801: 56058 | B12801: Harakiri | C12801: 1962 | D12801: Not Rated | E12801: 133 | G12801: Drama | H12801: 462030 | I12801: Masaki Kobayashi | J12801: 847668 | K12801: Yasuhiko Takiguchi | L12801: 410968 | M12801: Akira Ishihama | N12801: =INT(C12801/10)*10 & "-" & INT(C12801/10)*10+9 -> 1960-1969
...

Sheet Chart
A2: Row Labels | B2: Average of gross_us_canada
A3: Avengers: Endgame | B3: 858373000
A4: Spider-Man: No Way Home | B4: 814866759
A5: Top Gun: Maverick | B5: 718732821
A6: Avengers: Infinity War | B6: 678815482
A7: The Dark Knight | B7: 534987076
A8: Star Wars: Episode IV - A New Hope | B8: 460998507
A9: The Dark Knight Rises | B9: 448149584
A10: The Lion King | B10: 424979720
A11: Toy Story 3 | B11: 415004880
A12: Jurassic Park | B12: 407185075
A13: Grand Total | B13: 5.8148293e+08
A18: Row Labels | B18: Distinct Count of title
A19: Robert De Niro | B19: 9
A20: Tom Hanks | B20: 6
A21: Harrison Ford | B21: 6
A22: Leonardo DiCaprio | B22: 6
A23: Charles Chaplin | B23: 5
A24: Grand Total | B24: 31
A33: Row Labels | B33: Distinct Count of title
A34: R | B34: 102
A35: PG | B35: 38
A36: PG-13 | B36: 35
A37: Not Rated | B37: 23
A38: Approved | B38: 21
A39: G | B39: 18
A40: (blank) | B40: 6
A41: Passed | B41: 5
A42: TV-MA | B42: 1
A43: NC-17 | B43: 1
A44: Grand Total | B44: 250
A50: Distinct Count of title | B50: Column Labels
A51: Row Labels | B51: R | C51: PG | D51: PG-13 | E51: Not Rated | F51: Approved | G51: G | H51: (blank) | I51: Passed | J51: TV-MA | K51: NC-17 | L51: Grand Total
A52: Action | B52: 17 | C52: 7 | D52: 14 | E52: 4 | H52: 2 | I52: 2 | J52: 1 | L52: 47
A53: Action Epic | B53: 8 | C53: 6 | D53: 12 | E53: 1 | L53: 27
A54: Adult Animation | B54: 1 | D54: 1 | E54: 3 | J54: 1 | L54: 6
A55: Adventure | B55: 10 | C55: 18 | D55: 13 | E55: 1 | F55: 4 | G55: 11 | I55: 1 | J55: 1 | L55: 59
A56: Adventure Epic | B56: 4 | C56: 7 | D56: 8 | G56: 5 | L56: 24
A57: Alien Invasion | B57: 3 | C57: 1 | L57: 4
A58: Animal Adventure | C58: 1 | G58: 4 | L58: 5
A59: Animation | B59: 1 | C59: 11 | E59: 3 | G59: 8 | H59: 2 | L59: 25
A60: Anime | B60: 1 | C60: 2 | D60: 1 | E60: 2 | G60: 1 | H60: 2 | J60: 1 | L60: 10
A61: Artificial Intelligence | B61: 4 | C61: 2 | G61: 2 | L61: 8
A62: Biography | B62: 14 | C62: 3 | D62: 6 | E62: 1 | G62: 2 | H62: 1 | I62: 1 | L62: 28
A63: Body Horror | B63: 3 | L63: 3
A64: Boxing | B64: 1 | C64: 1 | D64: 2 | L64: 4
A65: Buddy Comedy | B65: 2 | C65: 2 | D65: 1 | F65: 1 | G65: 4 | I65: 1 | L65: 11
A66: Bumbling Detective | I66: 1 | L66: 1
A67: Caper | B67: 3 | C67: 1 | D67: 1 | L67: 5
A68: Car Action | B68: 1 | D68: 1 | L68: 2
A69: Classic Musical | G69: 3 | L69: 3
A70: Comedy | B70: 11 | C70: 9 | D70: 3 | E70: 2 | F70: 5 | G70: 10 | H70: 1 | I70: 3 | L70: 44
A71: Coming-of-Age | B71: 6 | C71: 7 | D71: 2 | E71: 4 | G71: 1 | L71: 20
A72: Computer Animation | C72: 8 | G72: 6 | L72: 14
A73: Conspiracy Thriller | B73: 2 | C73: 1 | L73: 3
A74: Contemporary Western | B74: 1 | L74: 1
A75: Cop Drama | B75: 5 | L75: 5
A76: Costume Drama | B76: 2 | C76: 2 | G76: 1 | I76: 1 | L76: 6
A77: Crime | B77: 34 | C77: 2 | D77: 4 | E77: 5 | F77: 6 | H77: 1 | I77: 1 | L77: 53
A78: Cyber Thriller | B78: 1 | L78: 1
A79: Cyberpunk | B79: 6 | L79: 6
A80: Dark Comedy | B80: 22 | C80: 4 | E80: 2 | F80: 2 | G80: 1 | L80: 31
A81: Dark Fantasy | B81: 2 | C81: 2 | D81: 4 | J81: 1 | L81: 9
A82: Dark Romance | B82: 2 | C82: 1 | E82: 1 | L82: 4
A83: Desert Adventure | B83: 2 | C83: 2 | D83: 3 | L83: 7
A84: Dinosaur Adventure | D84: 1 | L84: 1
A85: Disaster | B85: 1 | L85: 1
A86: Docudrama | B86: 15 | C86: 1 | D86: 5 | E86: 1 | H86: 1 | L86: 23
A87: Drama | B87: 83 | C87: 19 | D87: 26 | E87: 23 | F87: 18 | G87: 8 | H87: 4 | I87: 3 | K87: 1 | L87: 185
A88: Drug Crime | B88: 4 | L88: 4
A89: Dystopian Sci-Fi | B89: 8 | C89: 3 | E89: 1 | G89: 1 | L89: 13
A90: Epic | B90: 27 | C90: 8 | D90: 16 | E90: 3 | F90: 3 | G90: 6 | H90: 1 | L90: 64
A91: Erotic Thriller | B91: 2 | E91: 1 | L91: 3
A92: Fairy Tale | B92: 1 | C92: 1 | G92: 2 | L92: 4
A93: Family | C93: 13 | D93: 1 | E93: 1 | G93: 10 | I93: 1 | L93: 26
A94: Fantasy | B94: 2 | C94: 7 | D94: 5 | E94: 1 | G94: 5 | H94: 2 | L94: 22
A95: Fantasy Epic | C95: 3 | D95: 5 | G95: 1 | L95: 9
A96: Farce | B96: 1 | C96: 3 | F96: 3 | G96: 1 | I96: 3 | L96: 11
A97: Feel-Good Romance | B97: 2 | C97: 1 | F97: 3 | G97: 2 | I97: 1 | L97: 9
A98: Film Noir | F98: 3 | L98: 3
A99: Financial Drama | E99: 1 | L99: 1
A100: Gangster | B100: 15 | E100: 2 | L100: 17
A101: Globetrotting Adventure | C101: 4 | D101: 2 | L101: 6
A102: Gun Fu | B102: 1 | L102: 1
A103: Hand-Drawn Animation | B103: 1 | C103: 4 | D103: 1 | E103: 2 | G103: 2 | H103: 2 | J103: 1 | L103: 13
A104: Hard-boiled Detective | B104: 4 | F104: 2 | L104: 6
A105: Heist | B105: 4 | L105: 4
A106: High-Concept Comedy | C106: 4 | L106: 4
A107: Historical Epic | B107: 2 | D107: 1 | L107: 3
A108: History | B108: 5 | D108: 2 | F108: 1 | I108: 1 | L108: 9
A109: Holiday | B109: 1 | C109: 3 | D109: 1 | L109: 5
A110: Holiday Animation | C110: 1 | L110: 1
A111: Holiday Comedy | C111: 1 | F111: 1 | L111: 2
A112: Holiday Family | C112: 2 | L112: 2
A113: Holiday Romance | C113: 1 | F113: 1 | L113: 2
A114: Horror | B114: 7 | C114: 1 | L114: 8
A115: Iyashikei | G115: 1 | L115: 1
A116: Jukebox Musical | G116: 1 | L116: 1
A117: Jungle Adventure | C117: 1 | D117: 1 | G117: 1 | L117: 3
A118: Kaiju | C118: 1 | L118: 1
...

Sheet Report Chart
A2: IMDb Top 250 movies
B18: Top 5 Actors with the Most Appearances in IMDb Top 250 Movies
B19: Actor | G19: Number Of Appearances
B20: =Chart!$A19 -> Robert De Niro | G20: =GETPIVOTDATA("[Measures].[Distinct Count of title]",Chart!$A$18,"[Table2_1].[star.star]","[Table2_1].[star.star].&[Robert De Niro]") -> 9
B21: =Chart!$A20 -> Tom Hanks | G21: =GETPIVOTDATA("[Measures].[Distinct Count of title]",Chart!$A$18,"[Table2_1].[star.star]","[Table2_1].[star.star].&[Tom Hanks]") -> 6
B22: =Chart!$A21 -> Harrison Ford | G22: =GETPIVOTDATA("[Measures].[Distinct Count of title]",Chart!$A$18,"[Table2_1].[star.star]","[Table2_1].[star.star].&[Leonardo DiCaprio]") -> 6
B23: =Chart!$A22 -> Leonardo DiCaprio | G23: =GETPIVOTDATA("[Measures].[Distinct Count of title]",Chart!$A$18,"[Table2_1].[star.star]","[Table2_1].[star.star].&[Leonardo DiCaprio]") -> 6
B24: =Chart!$A23 -> Charles Chaplin | G24: =GETPIVOTDATA("[Measures].[Distinct Count of title]",Chart!$A$18,"[Table2_1].[star.star]","[Table2_1].[star.star].&[Charles Chaplin]") -> 5
B26: Number of films in each parental guide among the top 250 films on IMDB
B27: Parental Guide | G27: Number Of Movies
B28: =Chart!$A34 -> R | G28: =GETPIVOTDATA("[Measures].[Distinct Count of title]",Chart!$A$33,"[Table2_1].[parental_guide]","[Table2_1].[parental_guide].&[R]") -> 102
B29: =Chart!$A35 -> PG | G29: =GETPIVOTDATA("[Measures].[Distinct Count of title]",Chart!$A$33,"[Table2_1].[parental_guide]","[Table2_1].[parental_guide].&[PG]") -> 38
B30: =Chart!$A36 -> PG-13 | G30: =GETPIVOTDATA("[Measures].[Distinct Count of title]",Chart!$A$33,"[Table2_1].[parental_guide]","[Table2_1].[parental_guide].&[PG-13]") -> 35
B31: =Chart!$A37 -> Not Rated | G31: =GETPIVOTDATA("[Measures].[Distinct Count of title]",Chart!$A$33,"[Table2_1].[parental_guide]","[Table2_1].[parental_guide].&[Not Rated]") -> 23
B32: =Chart!$A38 -> Approved | G32: =GETPIVOTDATA("[Measures].[Distinct Count of title]",Chart!$A$33,"[Table2_1].[parental_guide]","[Table2_1].[parental_guide].&[Approved]") -> 21
B33: =Chart!$A39 -> G | G33: =GETPIVOTDATA("[Measures].[Distinct Count of title]",Chart!$A$33,"[Table2_1].[parental_guide]","[Table2_1].[parental_guide].&[G]") -> 18
B34: Without Parental Guide | G34: =GETPIVOTDATA("[Measures].[Distinct Count of title]",Chart!$A$33,"[Table2_1].[parental_guide]","[Table2_1].[parental_guide].&") -> 6
B35: =Chart!$A41 -> Passed | G35: =GETPIVOTDATA("[Measures].[Distinct Count of title]",Chart!$A$33,"[Table2_1].[parental_guide]","[Table2_1].[parental_guide].&[Passed]") -> 5
B36: =Chart!$A42 -> TV-MA | G36: =GETPIVOTDATA("[Measures].[Distinct Count of title]",Chart!$A$33,"[Table2_1].[parental_guide]","[Table2_1].[parental_guide].&[TV-MA]") -> 1
B37: =Chart!$A43 -> NC-17 | G37: =GETPIVOTDATA("[Measures].[Distinct Count of title]",Chart!$A$33,"[Table2_1].[parental_guide]","[Table2_1].[parental_guide].&[NC-17]") -> 1
B39: Number of each parental Guide in each genre among the top 250 movies on IMDB
F41: Count of title | G41: Parental Guide
F42: Genre | G42: Approved | H42: G | I42: NC-17 | J42: Not Rated | K42: Without PG | L42: Passed | M42: PG | N42: PG-13 | O42: R | P42: TV-MA | Q42: Grand Total
F43: Action | J43: 4 | K43: 2 | L43: 2 | M43: 7 | N43: 14 | O43: 17 | P43: 1 | Q43: 47
F44: Action Epic | J44: 1 | M44: 6 | N44: 12 | O44: 8 | Q44: 27
F45: Adult Animation | J45: 3 | N45: 1 | O45: 1 | P45: 1 | Q45: 6
F46: Adventure | G46: 4 | H46: 11 | J46: 1 | L46: 1 | M46: 18 | N46: 13 | O46: 10 | P46: 1 | Q46: 59
F47: Adventure Epic | H47: 5 | M47: 7 | N47: 8 | O47: 4 | Q47: 24
F48: Alien Invasion | M48: 1 | O48: 3 | Q48: 4
F49: Animal Adventure | H49: 4 | M49: 1 | Q49: 5
F50: Animation | H50: 8 | J50: 3 | K50: 2 | M50: 11 | O50: 1 | Q50: 25
F51: Anime | H51: 1 | J51: 2 | K51: 2 | M51: 2 | N51: 1 | O51: 1 | P51: 1 | Q51: 10
F52: Artificial Intelligence | H52: 2 | M52: 2 | O52: 4 | Q52: 8
F53: Biography | H53: 2 | J53: 1 | K53: 1 | L53: 1 | M53: 3 | N53: 6 | O53: 14 | Q53: 28
F54: Body Horror | O54: 3 | Q54: 3
F55: Boxing | M55: 1 | N55: 2 | O55: 1 | Q55: 4
F56: Buddy Comedy | G56: 1 | H56: 4 | L56: 1 | M56: 2 | N56: 1 | O56: 2 | Q56: 11
F57: Bumbling Detective | L57: 1 | Q57: 1
F58: Caper | M58: 1 | N58: 1 | O58: 3 | Q58: 5
F59: Car Action | N59: 1 | O59: 1 | Q59: 2
F60: Classic Musical | H60: 3 | Q60: 3
F61: Comedy | G61: 5 | H61: 10 | J61: 2 | K61: 1 | L61: 3 | M61: 9 | N61: 3 | O61: 11 | Q61: 44
F62: Coming-of-Age | H62: 1 | J62: 4 | M62: 7 | N62: 2 | O62: 6 | Q62: 20
F63: Computer Animation | H63: 6 | M63: 8 | Q63: 14
F64: Conspiracy Thriller | M64: 1 | O64: 2 | Q64: 3
F65: Contemporary Western | O65: 1 | Q65: 1
F66: Cop Drama | O66: 5 | Q66: 5
F67: Costume Drama | H67: 1 | L67: 1 | M67: 2 | O67: 2 | Q67: 6
F68: Crime | G68: 6 | J68: 5 | K68: 1 | L68: 1 | M68: 2 | N68: 4 | O68: 34 | Q68: 53
F69: Cyber Thriller | O69: 1 | Q69: 1
F70: Cyberpunk | O70: 6 | Q70: 6
F71: Dark Comedy | G71: 2 | H71: 1 | J71: 2 | M71: 4 | O71: 22 | Q71: 31
F72: Dark Fantasy | M72: 2 | N72: 4 | O72: 2 | P72: 1 | Q72: 9
F73: Dark Romance | J73: 1 | M73: 1 | O73: 2 | Q73: 4
F74: Desert Adventure | M74: 2 | N74: 3 | O74: 2 | Q74: 7
F75: Dinosaur Adventure | N75: 1 | Q75: 1
F76: Disaster | O76: 1 | Q76: 1
F77: Docudrama | J77: 1 | K77: 1 | M77: 1 | N77: 5 | O77: 15 | Q77: 23
F78: Drama | G78: 18 | H78: 8 | I78: 1 | J78: 23 | K78: 4 | L78: 3 | M78: 19 | N78: 26 | O78: 83 | Q78: 185
F79: Drug Crime | O79: 4 | Q79: 4
F80: Dystopian Sci-Fi | H80: 1 | J80: 1 | M80: 3 | O80: 8 | Q80: 13
F81: Epic | G81: 3 | H81: 6 | J81: 3 | K81: 1 | M81: 8 | N81: 16 | O81: 27 | Q81: 64
F82: Erotic Thriller | J82: 1 | O82: 2 | Q82: 3
F83: Fairy Tale | H83: 2 | M83: 1 | O83: 1 | Q83: 4
F84: Family | H84: 10 | J84: 1 | L84: 1 | M84: 13 | N84: 1 | Q84: 26
F85: Fantasy | H85: 5 | J85: 1 | K85: 2 | M85: 7 | N85: 5 | O85: 2 | Q85: 22
F86: Fantasy Epic | H86: 1 | M86: 3 | N86: 5 | Q86: 9
F87: Farce | G87: 3 | H87: 1 | L87: 3 | M87: 3 | O87: 1 | Q87: 11
F88: Feel-Good Romance | G88: 3 | H88: 2 | L88: 1 | M88: 1 | O88: 2 | Q88: 9
F89: Film Noir | G89: 3 | Q89: 3
F90: Financial Drama | J90: 1 | Q90: 1
F91: Gangster | J91: 2 | O91: 15 | Q91: 17
F92: Globetrotting Adventure | M92: 4 | N92: 2 | Q92: 6
F93: Gun Fu | O93: 1 | Q93: 1
F94: Hand-Drawn Animation | H94: 2 | J94: 2 | K94: 2 | M94: 4 | N94: 1 | O94: 1 | P94: 1 | Q94: 13
F95: Hard-boiled Detective | G95: 2 | O95: 4 | Q95: 6
F96: Heist | O96: 4 | Q96: 4
F97: High-Concept Comedy | M97: 4 | Q97: 4
F98: Historical Epic | N98: 1 | O98: 2 | Q98: 3
F99: History | G99: 1 | L99: 1 | N99: 2 | O99: 5 | Q99: 9
F100: Holiday | M100: 3 | N100: 1 | O100: 1 | Q100: 5
F101: Holiday Animation | M101: 1 | Q101: 1
F102: Holiday Comedy | G102: 1 | M102: 1 | Q102: 2
F103: Holiday Family | M103: 2 | Q103: 2
F104: Holiday Romance | G104: 1 | M104: 1 | Q104: 2
F105: Horror | M105: 1 | O105: 7 | Q105: 8
F106: Iyashikei | H106: 1 | Q106: 1
F107: Jukebox Musical | H107: 1 | Q107: 1
F108: Jungle Adventure | H108: 1 | M108: 1 | N108: 1 | Q108: 3
F109: Kaiju | M109: 1 | Q109: 1
F110: Kung Fu | O110: 1 | Q110: 1
F111: Legal Drama | G111: 7 | L111: 1 | N111: 1 | O111: 3 | Q111: 12
F112: Legal Thriller | G112: 2 | O112: 1 | Q112: 3
F113: Martial Arts | J113: 1 | O113: 2 | Q113: 3
F114: Medical Drama | O114: 1 | Q114: 1
F115: Monster Horror | M115: 1 | O115: 3 | Q115: 4
F116: Motorsport | N116: 1 | O116: 1 | Q116: 2
F117: Mountain Adventure | N117: 1 | Q117: 1
F118: Music | G118: 1 | M118: 2 | N118: 1 | O118: 2 | Q118: 6
F119: Musical | H119: 3 | N119: 1 | Q119: 4
...

Sheet Intractive Chart
A2: IMDb Top 250 movies
